fake_rpigpio/RPi.py
fake_rpigpio/__init__.py
fake_rpigpio/utils.py
fake_rpigpio-0.1.1.dist-info/LICENSE
fake_rpigpio-0.1.1.dist-info/METADATA
fake_rpigpio-0.1.1.dist-info/WHEEL
fake_rpigpio-0.1.1.dist-info/top_level.txt
fake_rpigpio-0.1.1.dist-info/RECORD
