Metadata-Version: 2.1
Name: fake_rpigpio
Version: 0.1.1
Summary: Fake Raspberry PI GPIO drop-in replacement for RPi.GPIO
Home-page: https://github.com/vapor-ware/fake-rpigpio
Author: Erick Daniszewski
Author-email: erick@vapor.io
License: GNU General Public License v3.0
Platform: UNKNOWN
Classifier: Intended Audience :: Developers
Classifier: Natural Language :: English
Classifier: Programming Language :: Python
Classifier: Topic :: Software Development :: Libraries
